[
  {
    "Seed": 1,
    "Personality": "Casual",
    "Passed": true,
    "Frames": 1485,
    "Events": 50,
    "ElapsedSec": 751.4,
    "ExitCode": -1073741819,
    "PSComputerName": "localhost",
    "RunspaceId": "5297399b-ca78-4eb1-b542-b95050bcd820",
    "PSShowComputerName": false
  },
  {
    "Seed": 1,
    "Personality": "Heretic",
    "Passed": true,
    "Frames": 746,
    "Events": 26,
    "ElapsedSec": 572.9,
    "ExitCode": -1073741819,
    "PSComputerName": "localhost",
    "RunspaceId": "b37f6d3d-e8f7-48d8-840f-5a8b5abe5047",
    "PSShowComputerName": false
  },
  {
    "Seed": 1,
    "Personality": "Magpie",
    "Passed": true,
    "Frames": 1999,
    "Events": 73,
    "ElapsedSec": 1557.3,
    "ExitCode": -1073741819,
    "PSComputerName": "localhost",
    "RunspaceId": "d1e1f258-764a-46ee-bf9f-695fe0652c9c",
    "PSShowComputerName": false
  },
  {
    "Seed": 1,
    "Personality": "Relay",
    "Passed": true,
    "Frames": 1010,
    "Events": 32,
    "ElapsedSec": 932.0,
    "ExitCode": -1073741819,
    "PSComputerName": "localhost",
    "RunspaceId": "f8946269-152d-41d7-81cd-0125e073a44c",
    "PSShowComputerName": false
  },
  {
    "Seed": 1,
    "Personality": "Speedrunner",
    "Passed": true,
    "Frames": 1382,
    "Events": 51,
    "ElapsedSec": 587.9,
    "ExitCode": -1073741819,
    "PSComputerName": "localhost",
    "RunspaceId": "2fddf917-45d2-47b3-9b58-2dca750fc69e",
    "PSShowComputerName": false
  },
  {
    "Seed": 1,
    "Personality": "Stealth",
    "Passed": true,
    "Frames": 1999,
    "Events": 33,
    "ElapsedSec": 1447.7,
    "ExitCode": -1073741819,
    "PSComputerName": "localhost",
    "RunspaceId": "2a12b769-02fb-4524-9e56-5d46d42a1c64",
    "PSShowComputerName": false
  },
  {
    "Seed": 1,
    "Personality": "Trickster",
    "Passed": true,
    "Frames": 1999,
    "Events": 83,
    "ElapsedSec": 1237.4,
    "ExitCode": -1073741819,
    "PSComputerName": "localhost",
    "RunspaceId": "49a9b4e0-255d-4fa3-bf24-55c82642ad91",
    "PSShowComputerName": false
  },
  {
    "Seed": 1,
    "Personality": "Zealot",
    "Passed": true,
    "Frames": 1999,
    "Events": 39,
    "ElapsedSec": 1441.0,
    "ExitCode": -1073741819,
    "PSComputerName": "localhost",
    "RunspaceId": "6ab51788-24a7-494d-bc3a-e04daaf1db40",
    "PSShowComputerName": false
  },
  {
    "Seed": 5,
    "Personality": "Casual",
    "Passed": true,
    "Frames": 1564,
    "Events": 38,
    "ElapsedSec": 62.5,
    "ExitCode": -1073741819,
    "PSComputerName": "localhost",
    "RunspaceId": "dbe1bfd6-2956-4e36-be89-1c18dd75205f",
    "PSShowComputerName": false
  },
  {
    "Seed": 5,
    "Personality": "Heretic",
    "Passed": true,
    "Frames": 783,
    "Events": 28,
    "ElapsedSec": 39.0,
    "ExitCode": -1073741819,
    "PSComputerName": "localhost",
    "RunspaceId": "676619a7-2ae3-41ed-96bd-d1a404ab96cb",
    "PSShowComputerName": false
  },
  {
    "Seed": 5,
    "Personality": "Magpie",
    "Passed": true,
    "Frames": 1106,
    "Events": 46,
    "ElapsedSec": 55.5,
    "ExitCode": -1073741819,
    "PSComputerName": "localhost",
    "RunspaceId": "0b2f6093-2aeb-403f-a9b4-2f8004f0e91b",
    "PSShowComputerName": false
  },
  {
    "Seed": 5,
    "Personality": "Relay",
    "Passed": true,
    "Frames": 766,
    "Events": 23,
    "ElapsedSec": 30.8,
    "ExitCode": -1073741819,
    "PSComputerName": "localhost",
    "RunspaceId": "21cbe7ae-6ba7-4bf3-91a8-a89c508d506a",
    "PSShowComputerName": false
  },
  {
    "Seed": 5,
    "Personality": "Speedrunner",
    "Passed": true,
    "Frames": 1420,
    "Events": 54,
    "ElapsedSec": 67.0,
    "ExitCode": -1073741819,
    "PSComputerName": "localhost",
    "RunspaceId": "58e518c0-8733-461f-ad4a-4f8ba28f7241",
    "PSShowComputerName": false
  },
  {
    "Seed": 5,
    "Personality": "Stealth",
    "Passed": true,
    "Frames": 1702,
    "Events": 30,
    "ElapsedSec": 65.3,
    "ExitCode": -1073741819,
    "PSComputerName": "localhost",
    "RunspaceId": "8a8c9570-4896-4381-aa7e-87e1d2740681",
    "PSShowComputerName": false
  },
  {
    "Seed": 5,
    "Personality": "Trickster",
    "Passed": true,
    "Frames": 1706,
    "Events": 61,
    "ElapsedSec": 70.9,
    "ExitCode": -1073741819,
    "PSComputerName": "localhost",
    "RunspaceId": "11cffebe-4152-44dc-a185-34ae338ce5ab",
    "PSShowComputerName": false
  },
  {
    "Seed": 5,
    "Personality": "Zealot",
    "Passed": true,
    "Frames": 1294,
    "Events": 38,
    "ElapsedSec": 46.8,
    "ExitCode": -1073741819,
    "PSComputerName": "localhost",
    "RunspaceId": "cd627436-c16c-4088-b562-c26958ba11da",
    "PSShowComputerName": false
  },
  {
    "Seed": 7,
    "Personality": "Casual",
    "Passed": true,
    "Frames": 1756,
    "Events": 48,
    "ElapsedSec": 66.4,
    "ExitCode": -1073741819,
    "PSComputerName": "localhost",
    "RunspaceId": "c6d8e02d-c4aa-40b9-aca0-0440d45c4d55",
    "PSShowComputerName": false
  },
  {
    "Seed": 7,
    "Personality": "Heretic",
    "Passed": true,
    "Frames": 1999,
    "Events": 75,
    "ElapsedSec": 108.2,
    "ExitCode": -1073741819,
    "PSComputerName": "localhost",
    "RunspaceId": "ce0b8885-3dcb-440e-b7c8-53011f6b75a2",
    "PSShowComputerName": false
  },
  {
    "Seed": 7,
    "Personality": "Magpie",
    "Passed": true,
    "Frames": 1999,
    "Events": 74,
    "ElapsedSec": 96.1,
    "ExitCode": -1073741819,
    "PSComputerName": "localhost",
    "RunspaceId": "d7fc6cfa-0384-4731-94ec-b170e9e569e1",
    "PSShowComputerName": false
  },
  {
    "Seed": 7,
    "Personality": "Relay",
    "Passed": true,
    "Frames": 1872,
    "Events": 56,
    "ElapsedSec": 61.8,
    "ExitCode": -1073741819,
    "PSComputerName": "localhost",
    "RunspaceId": "958edc6c-6451-4a82-b095-0d78c35074d3",
    "PSShowComputerName": false
  },
  {
    "Seed": 7,
    "Personality": "Speedrunner",
    "Passed": true,
    "Frames": 1999,
    "Events": 81,
    "ElapsedSec": 94.1,
    "ExitCode": -1073741819,
    "PSComputerName": "localhost",
    "RunspaceId": "7673b937-8d8b-4960-8f0c-d9c626fc9c6d",
    "PSShowComputerName": false
  },
  {
    "Seed": 7,
    "Personality": "Stealth",
    "Passed": true,
    "Frames": 1569,
    "Events": 49,
    "ElapsedSec": 77.2,
    "ExitCode": -1073741819,
    "PSComputerName": "localhost",
    "RunspaceId": "69e7b056-33ea-4e5a-b39a-6f9243a2c37e",
    "PSShowComputerName": false
  },
  {
    "Seed": 7,
    "Personality": "Trickster",
    "Passed": true,
    "Frames": 817,
    "Events": 39,
    "ElapsedSec": 45.4,
    "ExitCode": -1073741819,
    "PSComputerName": "localhost",
    "RunspaceId": "58c17d14-cf2e-43c3-92e6-f53106cbeeb4",
    "PSShowComputerName": false
  },
  {
    "Seed": 7,
    "Personality": "Zealot",
    "Passed": true,
    "Frames": 1999,
    "Events": 63,
    "ElapsedSec": 74.5,
    "ExitCode": -1073741819,
    "PSComputerName": "localhost",
    "RunspaceId": "d7e4fdef-4562-46ec-bf2b-0bd6974f0529",
    "PSShowComputerName": false
  },
  {
    "Seed": 42,
    "Personality": "Casual",
    "Passed": true,
    "Frames": 1176,
    "Events": 39,
    "ElapsedSec": 59.5,
    "ExitCode": -1073741819,
    "PSComputerName": "localhost",
    "RunspaceId": "4f27c5d6-5c65-4536-b8be-acf8e44ea86d",
    "PSShowComputerName": false
  },
  {
    "Seed": 42,
    "Personality": "Heretic",
    "Passed": true,
    "Frames": 705,
    "Events": 26,
    "ElapsedSec": 41.1,
    "ExitCode": -1073741819,
    "PSComputerName": "localhost",
    "RunspaceId": "e1e8b01a-15de-4f6f-be70-b492999f1c7e",
    "PSShowComputerName": false
  },
  {
    "Seed": 42,
    "Personality": "Magpie",
    "Passed": true,
    "Frames": 1050,
    "Events": 57,
    "ElapsedSec": 71.2,
    "ExitCode": -1073741819,
    "PSComputerName": "localhost",
    "RunspaceId": "f121eaf9-4952-4848-85b3-e38b54d21a72",
    "PSShowComputerName": false
  },
  {
    "Seed": 42,
    "Personality": "Relay",
    "Passed": true,
    "Frames": 900,
    "Events": 30,
    "ElapsedSec": 39.1,
    "ExitCode": -1073741819,
    "PSComputerName": "localhost",
    "RunspaceId": "4f3f4b2b-fed7-405e-920f-8df7b4267d72",
    "PSShowComputerName": false
  },
  {
    "Seed": 42,
    "Personality": "Speedrunner",
    "Passed": true,
    "Frames": 864,
    "Events": 50,
    "ElapsedSec": 71.3,
    "ExitCode": -1073741819,
    "PSComputerName": "localhost",
    "RunspaceId": "2c6560a7-b27c-4716-8c93-25ee7154916a",
    "PSShowComputerName": false
  },
  {
    "Seed": 42,
    "Personality": "Stealth",
    "Passed": true,
    "Frames": 1599,
    "Events": 43,
    "ElapsedSec": 70.8,
    "ExitCode": -1073741819,
    "PSComputerName": "localhost",
    "RunspaceId": "748c9f9d-7aee-4f91-a31d-71143d9e9122",
    "PSShowComputerName": false
  },
  {
    "Seed": 42,
    "Personality": "Trickster",
    "Passed": true,
    "Frames": 933,
    "Events": 55,
    "ElapsedSec": 69.0,
    "ExitCode": -1073741819,
    "PSComputerName": "localhost",
    "RunspaceId": "fb7f69f6-c3ae-4d1a-8edf-48739da96d29",
    "PSShowComputerName": false
  },
  {
    "Seed": 42,
    "Personality": "Zealot",
    "Passed": true,
    "Frames": 751,
    "Events": 24,
    "ElapsedSec": 31.8,
    "ExitCode": -1073741819,
    "PSComputerName": "localhost",
    "RunspaceId": "36fec792-ba65-4a36-a5b3-5cd930152d36",
    "PSShowComputerName": false
  },
  {
    "Seed": 100,
    "Personality": "Casual",
    "Passed": true,
    "Frames": 1999,
    "Events": 45,
    "ElapsedSec": 89.8,
    "ExitCode": -1073741819,
    "PSComputerName": "localhost",
    "RunspaceId": "89e185e1-de3a-4fe9-b8f3-8df6e2f1f173",
    "PSShowComputerName": false
  },
  {
    "Seed": 100,
    "Personality": "Heretic",
    "Passed": true,
    "Frames": 1071,
    "Events": 35,
    "ElapsedSec": 47.7,
    "ExitCode": -1073741819,
    "PSComputerName": "localhost",
    "RunspaceId": "924cc9a4-9629-4d6f-ada0-445c2c83739a",
    "PSShowComputerName": false
  },
  {
    "Seed": 100,
    "Personality": "Magpie",
    "Passed": true,
    "Frames": 1470,
    "Events": 63,
    "ElapsedSec": 77.0,
    "ExitCode": -1073741819,
    "PSComputerName": "localhost",
    "RunspaceId": "361ef9d5-fff7-4cf9-b6cb-416932bd36ac",
    "PSShowComputerName": false
  },
  {
    "Seed": 100,
    "Personality": "Relay",
    "Passed": true,
    "Frames": 1699,
    "Events": 45,
    "ElapsedSec": 59.4,
    "ExitCode": -1073741819,
    "PSComputerName": "localhost",
    "RunspaceId": "73ddacc4-3857-421a-8bae-9428014fd3f9",
    "PSShowComputerName": false
  },
  {
    "Seed": 100,
    "Personality": "Speedrunner",
    "Passed": true,
    "Frames": 1767,
    "Events": 65,
    "ElapsedSec": 86.3,
    "ExitCode": -1073741819,
    "PSComputerName": "localhost",
    "RunspaceId": "bba8d6df-eed4-463a-8a6c-cd9198689563",
    "PSShowComputerName": false
  },
  {
    "Seed": 100,
    "Personality": "Stealth",
    "Passed": true,
    "Frames": 1999,
    "Events": 47,
    "ElapsedSec": 78.3,
    "ExitCode": -1073741819,
    "PSComputerName": "localhost",
    "RunspaceId": "3ace234d-ccdd-43da-8159-4887f794c815",
    "PSShowComputerName": false
  },
  {
    "Seed": 100,
    "Personality": "Trickster",
    "Passed": true,
    "Frames": 1695,
    "Events": 67,
    "ElapsedSec": 446.0,
    "ExitCode": -1073741819,
    "PSComputerName": "localhost",
    "RunspaceId": "741e2754-7f55-4fde-b527-656481a86d1f",
    "PSShowComputerName": false
  },
  {
    "Seed": 100,
    "Personality": "Zealot",
    "Passed": true,
    "Frames": 1999,
    "Events": 46,
    "ElapsedSec": 70.8,
    "ExitCode": -1073741819,
    "PSComputerName": "localhost",
    "RunspaceId": "24f25959-4cb6-435d-8875-47e745847569",
    "PSShowComputerName": false
  },
  {
    "Seed": 12345,
    "Personality": "Casual",
    "Passed": true,
    "Frames": 1941,
    "Events": 67,
    "ElapsedSec": 108.2,
    "ExitCode": -1073741819,
    "PSComputerName": "localhost",
    "RunspaceId": "0d7387bd-4651-45aa-93ce-1389c0651e9d",
    "PSShowComputerName": false
  },
  {
    "Seed": 12345,
    "Personality": "Heretic",
    "Passed": true,
    "Frames": 1689,
    "Events": 45,
    "ElapsedSec": 244.0,
    "ExitCode": -1073741819,
    "PSComputerName": "localhost",
    "RunspaceId": "3a8a58b9-6aef-4ea8-bcdb-6697376c9220",
    "PSShowComputerName": false
  },
  {
    "Seed": 12345,
    "Personality": "Magpie",
    "Passed": true,
    "Frames": 1265,
    "Events": 59,
    "ElapsedSec": 73.5,
    "ExitCode": -1073741819,
    "PSComputerName": "localhost",
    "RunspaceId": "8456b2ca-601c-4dec-99f5-ee70eea95a28",
    "PSShowComputerName": false
  },
  {
    "Seed": 12345,
    "Personality": "Relay",
    "Passed": true,
    "Frames": 1999,
    "Events": 53,
    "ElapsedSec": 73.0,
    "ExitCode": -1073741819,
    "PSComputerName": "localhost",
    "RunspaceId": "124d83db-798a-45bb-812d-47289aa8aaf7",
    "PSShowComputerName": false
  },
  {
    "Seed": 12345,
    "Personality": "Speedrunner",
    "Passed": true,
    "Frames": 1999,
    "Events": 64,
    "ElapsedSec": 79.7,
    "ExitCode": -1073741819,
    "PSComputerName": "localhost",
    "RunspaceId": "a1d64da7-09a6-4a84-b4ba-3ef0e3fb1f91",
    "PSShowComputerName": false
  },
  {
    "Seed": 12345,
    "Personality": "Stealth",
    "Passed": true,
    "Frames": 1999,
    "Events": 49,
    "ElapsedSec": 83.8,
    "ExitCode": -1073741819,
    "PSComputerName": "localhost",
    "RunspaceId": "4f09b9ee-adfe-4e26-8010-c166b59587e1",
    "PSShowComputerName": false
  },
  {
    "Seed": 12345,
    "Personality": "Trickster",
    "Passed": true,
    "Frames": 1999,
    "Events": 68,
    "ElapsedSec": 82.9,
    "ExitCode": -1073741819,
    "PSComputerName": "localhost",
    "RunspaceId": "24011d7d-4513-4f71-a334-c127d0664622",
    "PSShowComputerName": false
  },
  {
    "Seed": 12345,
    "Personality": "Zealot",
    "Passed": true,
    "Frames": 1999,
    "Events": 54,
    "ElapsedSec": 62.5,
    "ExitCode": -1073741819,
    "PSComputerName": "localhost",
    "RunspaceId": "309f3e22-daf8-4e61-bf61-f221626252de",
    "PSShowComputerName": false
  },
  {
    "Seed": 55555,
    "Personality": "Casual",
    "Passed": true,
    "Frames": 1999,
    "Events": 33,
    "ElapsedSec": 368.7,
    "ExitCode": -1073741819,
    "PSComputerName": "localhost",
    "RunspaceId": "be675e94-4c46-4c4e-a418-d2f8b208aabb",
    "PSShowComputerName": false
  },
  {
    "Seed": 55555,
    "Personality": "Heretic",
    "Passed": true,
    "Frames": 1903,
    "Events": 41,
    "ElapsedSec": 350.9,
    "ExitCode": -1073741819,
    "PSComputerName": "localhost",
    "RunspaceId": "b107c6f6-93a9-48fd-a8d1-4bac52eb8529",
    "PSShowComputerName": false
  },
  {
    "Seed": 55555,
    "Personality": "Magpie",
    "Passed": true,
    "Frames": 1999,
    "Events": 54,
    "ElapsedSec": 372.4,
    "ExitCode": -1073741819,
    "PSComputerName": "localhost",
    "RunspaceId": "e7bfd3de-32a7-489f-bfb4-91ce8439bcee",
    "PSShowComputerName": false
  },
  {
    "Seed": 55555,
    "Personality": "Relay",
    "Passed": true,
    "Frames": 1999,
    "Events": 29,
    "ElapsedSec": 346.7,
    "ExitCode": -1073741819,
    "PSComputerName": "localhost",
    "RunspaceId": "a123501f-2b7c-4ba6-9f3f-0df9fd70085e",
    "PSShowComputerName": false
  },
  {
    "Seed": 55555,
    "Personality": "Speedrunner",
    "Passed": true,
    "Frames": 1668,
    "Events": 44,
    "ElapsedSec": 356.5,
    "ExitCode": -1073741819,
    "PSComputerName": "localhost",
    "RunspaceId": "9b5aa0f4-1841-43be-b2ea-27e20f808622",
    "PSShowComputerName": false
  },
  {
    "Seed": 55555,
    "Personality": "Stealth",
    "Passed": true,
    "Frames": 1999,
    "Events": 23,
    "ElapsedSec": 806.2,
    "ExitCode": -1073741819,
    "PSComputerName": "localhost",
    "RunspaceId": "a074e109-9e1c-43f7-b9de-1b84e728a49b",
    "PSShowComputerName": false
  },
  {
    "Seed": 55555,
    "Personality": "Trickster",
    "Passed": true,
    "Frames": 1999,
    "Events": 67,
    "ElapsedSec": 374.5,
    "ExitCode": -1073741819,
    "PSComputerName": "localhost",
    "RunspaceId": "9ea9a16e-37c8-4da1-b68e-1afcbc05f3f2",
    "PSShowComputerName": false
  },
  {
    "Seed": 55555,
    "Personality": "Zealot",
    "Passed": true,
    "Frames": 1999,
    "Events": 42,
    "ElapsedSec": 491.5,
    "ExitCode": -1073741819,
    "PSComputerName": "localhost",
    "RunspaceId": "8f70576f-3d0b-4b49-9296-dee9b826666d",
    "PSShowComputerName": false
  },
  {
    "Seed": 99999,
    "Personality": "Casual",
    "Passed": true,
    "Frames": 1999,
    "Events": 46,
    "ElapsedSec": 71.0,
    "ExitCode": -1073741819,
    "PSComputerName": "localhost",
    "RunspaceId": "ffb39632-ef26-4a5b-9c82-42bb1706839d",
    "PSShowComputerName": false
  },
  {
    "Seed": 99999,
    "Personality": "Heretic",
    "Passed": true,
    "Frames": 1140,
    "Events": 42,
    "ElapsedSec": 54.5,
    "ExitCode": -1073741819,
    "PSComputerName": "localhost",
    "RunspaceId": "19085dc0-e001-407b-b3f7-6812cc34aeee",
    "PSShowComputerName": false
  },
  {
    "Seed": 99999,
    "Personality": "Magpie",
    "Passed": true,
    "Frames": 1050,
    "Events": 39,
    "ElapsedSec": 53.9,
    "ExitCode": -1073741819,
    "PSComputerName": "localhost",
    "RunspaceId": "a8b2ee17-8b2a-427d-9abd-71a5f728e4cd",
    "PSShowComputerName": false
  },
  {
    "Seed": 99999,
    "Personality": "Relay",
    "Passed": true,
    "Frames": 917,
    "Events": 39,
    "ElapsedSec": 41.1,
    "ExitCode": -1073741819,
    "PSComputerName": "localhost",
    "RunspaceId": "23ce73c6-d46e-4375-b518-04c14aa31ca7",
    "PSShowComputerName": false
  },
  {
    "Seed": 99999,
    "Personality": "Speedrunner",
    "Passed": true,
    "Frames": 1352,
    "Events": 50,
    "ElapsedSec": 64.8,
    "ExitCode": -1073741819,
    "PSComputerName": "localhost",
    "RunspaceId": "2fbc045b-6b85-427a-8671-b78ccb8b61b9",
    "PSShowComputerName": false
  },
  {
    "Seed": 99999,
    "Personality": "Stealth",
    "Passed": true,
    "Frames": 1999,
    "Events": 41,
    "ElapsedSec": 70.8,
    "ExitCode": -1073741819,
    "PSComputerName": "localhost",
    "RunspaceId": "04fa4dc7-483f-40d2-9676-cb43df69b456",
    "PSShowComputerName": false
  },
  {
    "Seed": 99999,
    "Personality": "Trickster",
    "Passed": true,
    "Frames": 1050,
    "Events": 39,
    "ElapsedSec": 51.6,
    "ExitCode": -1073741819,
    "PSComputerName": "localhost",
    "RunspaceId": "40b2511f-f70b-49e0-b226-f34699ebbe78",
    "PSShowComputerName": false
  },
  {
    "Seed": 99999,
    "Personality": "Zealot",
    "Passed": true,
    "Frames": 880,
    "Events": 32,
    "ElapsedSec": 39.3,
    "ExitCode": -1073741819,
    "PSComputerName": "localhost",
    "RunspaceId": "41a30c6d-b608-4d9f-9e23-d88ba3991c5f",
    "PSShowComputerName": false
  },
  {
    "Seed": 250000,
    "Personality": "Casual",
    "Passed": true,
    "Frames": 1999,
    "Events": 35,
    "ElapsedSec": 325.7,
    "ExitCode": -1073741819,
    "PSComputerName": "localhost",
    "RunspaceId": "cf892277-f9c7-4d66-a051-9ae2b4926a7a",
    "PSShowComputerName": false
  },
  {
    "Seed": 250000,
    "Personality": "Heretic",
    "Passed": true,
    "Frames": 1999,
    "Events": 64,
    "ElapsedSec": 81.0,
    "ExitCode": -1073741819,
    "PSComputerName": "localhost",
    "RunspaceId": "63362874-2304-493a-b6be-610dd47902f2",
    "PSShowComputerName": false
  },
  {
    "Seed": 250000,
    "Personality": "Magpie",
    "Passed": true,
    "Frames": 1999,
    "Events": 37,
    "ElapsedSec": 361.2,
    "ExitCode": -1073741819,
    "PSComputerName": "localhost",
    "RunspaceId": "447e1bec-9641-4aa6-995b-67ac28a1c33d",
    "PSShowComputerName": false
  },
  {
    "Seed": 250000,
    "Personality": "Relay",
    "Passed": true,
    "Frames": 1999,
    "Events": 110,
    "ElapsedSec": 150.4,
    "ExitCode": -1073741819,
    "PSComputerName": "localhost",
    "RunspaceId": "b3a7725b-a26e-4f48-b943-682b6d0cccd7",
    "PSShowComputerName": false
  },
  {
    "Seed": 250000,
    "Personality": "Speedrunner",
    "Passed": true,
    "Frames": 1999,
    "Events": 60,
    "ElapsedSec": 383.2,
    "ExitCode": -1073741819,
    "PSComputerName": "localhost",
    "RunspaceId": "d1fc8b37-d7e9-4543-aae7-54096bc61591",
    "PSShowComputerName": false
  },
  {
    "Seed": 250000,
    "Personality": "Stealth",
    "Passed": true,
    "Frames": 1999,
    "Events": 30,
    "ElapsedSec": 500.1,
    "ExitCode": -1073741819,
    "PSComputerName": "localhost",
    "RunspaceId": "44156243-4002-4148-b9ab-0620df881c2b",
    "PSShowComputerName": false
  },
  {
    "Seed": 250000,
    "Personality": "Trickster",
    "Passed": true,
    "Frames": 1910,
    "Events": 72,
    "ElapsedSec": 358.8,
    "ExitCode": -1073741819,
    "PSComputerName": "localhost",
    "RunspaceId": "7419b4c8-f68b-42c5-960f-3ea57dbb61c1",
    "PSShowComputerName": false
  },
  {
    "Seed": 250000,
    "Personality": "Zealot",
    "Passed": true,
    "Frames": 1999,
    "Events": 91,
    "ElapsedSec": 96.1,
    "ExitCode": -1073741819,
    "PSComputerName": "localhost",
    "RunspaceId": "62be5bcd-4031-4322-8863-dbe7c187b83d",
    "PSShowComputerName": false
  },
  {
    "Seed": 4276994270,
    "Personality": "Casual",
    "Passed": true,
    "Frames": 1433,
    "Events": 43,
    "ElapsedSec": 56.0,
    "ExitCode": -1073741819,
    "PSComputerName": "localhost",
    "RunspaceId": "297108d0-c72d-433a-8cba-2a46ee07d103",
    "PSShowComputerName": false
  },
  {
    "Seed": 4276994270,
    "Personality": "Heretic",
    "Passed": true,
    "Frames": 1117,
    "Events": 58,
    "ElapsedSec": 43.2,
    "ExitCode": -1073741819,
    "PSComputerName": "localhost",
    "RunspaceId": "d1475cf3-efd1-477f-b806-271fad006672",
    "PSShowComputerName": false
  },
  {
    "Seed": 4276994270,
    "Personality": "Magpie",
    "Passed": true,
    "Frames": 1302,
    "Events": 59,
    "ElapsedSec": 59.1,
    "ExitCode": -1073741819,
    "PSComputerName": "localhost",
    "RunspaceId": "c661758c-2edb-47ce-b739-a3c8c28c2fca",
    "PSShowComputerName": false
  },
  {
    "Seed": 4276994270,
    "Personality": "Relay",
    "Passed": true,
    "Frames": 1079,
    "Events": 48,
    "ElapsedSec": 40.0,
    "ExitCode": -1073741819,
    "PSComputerName": "localhost",
    "RunspaceId": "e0bdc912-4cf9-4c46-a095-6e3471a3fc6e",
    "PSShowComputerName": false
  },
  {
    "Seed": 4276994270,
    "Personality": "Speedrunner",
    "Passed": true,
    "Frames": 1999,
    "Events": 53,
    "ElapsedSec": 66.2,
    "ExitCode": -1073741819,
    "PSComputerName": "localhost",
    "RunspaceId": "831f94d4-b52f-4dab-ade7-93044eab5882",
    "PSShowComputerName": false
  },
  {
    "Seed": 4276994270,
    "Personality": "Stealth",
    "Passed": true,
    "Frames": 1999,
    "Events": 47,
    "ElapsedSec": 62.0,
    "ExitCode": -1073741819,
    "PSComputerName": "localhost",
    "RunspaceId": "6d60ae07-1fee-47a2-a2b6-ba5285eedffd",
    "PSShowComputerName": false
  },
  {
    "Seed": 4276994270,
    "Personality": "Trickster",
    "Passed": true,
    "Frames": 1999,
    "Events": 76,
    "ElapsedSec": 62.5,
    "ExitCode": -1073741819,
    "PSComputerName": "localhost",
    "RunspaceId": "73920a4c-3bec-4f3e-ad75-b0fb801c6d22",
    "PSShowComputerName": false
  },
  {
    "Seed": 4276994270,
    "Personality": "Zealot",
    "Passed": true,
    "Frames": 1116,
    "Events": 50,
    "ElapsedSec": 42.2,
    "ExitCode": -1073741819,
    "PSComputerName": "localhost",
    "RunspaceId": "819a8764-f6d1-4ff4-b4b1-ecc4354dac2c",
    "PSShowComputerName": false
  }
]
