{
  "levelNumber": 4,
  "gridWidth": 8,
  "gridHeight": 8,
  "minimumMoves": 8,
  "grid": [
    "........",
    ".######.",
    ".######.",
    ".######.",
    ".######.",
    ".######.",
    ".######.",
    "........"
  ],
  "shapes": [
    {
      "color": "None",
      "originX": 1,
      "originY": 6,
      "type": "Single",
      "draggable": false,
      "cells": [[0, 0]]
    },
    {
      "color": "None",
      "originX": 5,
      "originY": 5,
      "type": "Single",
      "draggable": false,
      "cells": [[0, 0]]
    },
    {
      "color": "None",
      "originX": 2,
      "originY": 6,
      "type": "Single",
      "draggable": false,
      "cells": [[0, 0]]
    },
    {
      "color": "Red",
      "originX": 1,
      "originY": 2,
      "type": "L",
      "draggable": true,
      "cells": [[0, 0], [1, 0], [2, 0], [2, 1]]
      ,"unlockThreshold": 2
    },
    {
      "color": "Green",
      "originX": 4,
      "originY": 3,
      "type": "I",
      "draggable": true,
      "cells": [[0, 0], [1, 0], [2, 0]]
    },
    {
      "color": "Blue",
      "originX": 1,
      "originY": 4,
      "type": "I",
      "draggable": true,
      "cells": [[0, 0], [1, 0], [2, 0]]
    }
  ],
  "cats": [
    {
      "color": "Red",
      "gridX": 2,
      "gridY": 1,
      "onBlocker": false
    },
    {
      "color": "Red",
      "gridX": 5,
      "gridY": 2,
      "onBlocker": false
    },
    {
      "color": "Red",
      "gridX": 6,
      "gridY": 5,
      "onBlocker": false
    },
    {
      "color": "Green",
      "gridX": 1,
      "gridY": 3,
      "onBlocker": false
    },
    {
      "color": "Green",
      "gridX": 4,
      "gridY": 2,
      "onBlocker": false
    },
    {
      "color": "Green",
      "gridX": 4,
      "gridY": 5,
      "onBlocker": false
    },
    {
      "color": "Blue",
      "gridX": 1,
      "gridY": 5,
      "onBlocker": false
    },
    {
      "color": "Blue",
      "gridX": 3,
      "gridY": 5,
      "onBlocker": false
    },
    {
      "color": "Blue",
      "gridX": 6,
      "gridY": 2,
      "onBlocker": false
    }
  ],
  "analytics": {
    "generationTimeMs": 237200.7,
    "numColors": 3,
    "numCatsPerColor": 3,
    "maxShapeComplexity": 3,
    "totalAttempts": 1000,
    "scrambleFailures": 382,
    "solverTooEasy": 395,
    "solverUnsolvable": 178
  }
}
