{
  "levelNumber": 2,
  "gridWidth": 8,
  "gridHeight": 8,
  "minimumMoves": 7,
  "grid": [
    "........",
    ".######.",
    ".######.",
    ".######.",
    ".######.",
    ".######.",
    ".######.",
    "........"
  ],
  "shapes": [
    {
      "color": "None",
      "originX": 6,
      "originY": 2,
      "type": "Single",
      "draggable": false,
      "cells": [[0, 0]]
    },
    {
      "color": "None",
      "originX": 1,
      "originY": 2,
      "type": "Single",
      "draggable": false,
      "cells": [[0, 0]]
    },
    {
      "color": "None",
      "originX": 5,
      "originY": 2,
      "type": "Single",
      "draggable": false,
      "cells": [[0, 0]]
    },
    {
      "color": "Red",
      "originX": 4,
      "originY": 6,
      "type": "I",
      "draggable": true,
      "cells": [[0, 0], [1, 0], [2, 0]]
      ,"unlockThreshold": 2
    },
    {
      "color": "Green",
      "originX": 1,
      "originY": 5,
      "type": "L",
      "draggable": true,
      "cells": [[0, 0], [1, 0], [2, 0], [2, 1]]
    },
    {
      "color": "Blue",
      "originX": 4,
      "originY": 4,
      "type": "L",
      "draggable": true,
      "cells": [[0, 0], [1, 0], [2, 0], [2, 1]]
    }
  ],
  "cats": [
    {
      "color": "Red",
      "gridX": 4,
      "gridY": 5,
      "onBlocker": false
    },
    {
      "color": "Red",
      "gridX": 5,
      "gridY": 1,
      "onBlocker": false
    },
    {
      "color": "Green",
      "gridX": 3,
      "gridY": 4,
      "onBlocker": false
    },
    {
      "color": "Green",
      "gridX": 2,
      "gridY": 2,
      "onBlocker": false
    },
    {
      "color": "Blue",
      "gridX": 2,
      "gridY": 3,
      "onBlocker": false
    },
    {
      "color": "Blue",
      "gridX": 4,
      "gridY": 1,
      "onBlocker": false
    }
  ],
  "analytics": {
    "generationTimeMs": 160623.9,
    "numColors": 3,
    "numCatsPerColor": 2,
    "maxShapeComplexity": 3,
    "totalAttempts": 1000,
    "scrambleFailures": 336,
    "solverTooEasy": 436,
    "solverUnsolvable": 173
  }
}
